aurori/LICENSE.md
aurori/README.md
aurori/__init__.py
aurori/alembic.ini
aurori/config.py
aurori/database.py
aurori/routes.py
aurori/version.py
aurori/api/__init__.py
aurori/api/dependencies.py
aurori/api/security.py
aurori/cli/__init__.py
aurori/cli/core.py
aurori/features/__init__.py
aurori/features/database.py
aurori/features/feature.py
aurori/features/featureManager.py
aurori/features/page.py
aurori/features/permission.py
aurori/features/routes.py
aurori/logs/__init__.py
aurori/logs/logManager.py
aurori/logs/logger.py
aurori/logs/routes.py
aurori/migrations/README.md
aurori/migrations/env.py
aurori/migrations/script.py.mako
aurori/pages/__init__.py
aurori/pages/menuBuilder.py
aurori/runners/__init__.py
aurori/runners/database.py
aurori/runners/routes.py
aurori/runners/runner.py
aurori/runners/runnerManager.py
aurori/types/exceptions.py
aurori/types/intEnum.py
aurori/types/intFlag.py
aurori/types/jsonDict.py
aurori/types/objDict.py
aurori/users/__init__.py
aurori/users/defaultuser.py
aurori/users/dependencies.py
aurori/users/routes.py
aurori/users/typemodels.py
aurori/users/userManager.py
aurori/users/userbase.py
aurori/utils/__init__.py
aurori/utils/converter.py
aurori-1.4.1.dist-info/LICENSE
aurori-1.4.1.dist-info/METADATA
aurori-1.4.1.dist-info/WHEEL
aurori-1.4.1.dist-info/entry_points.txt
aurori-1.4.1.dist-info/top_level.txt
aurori-1.4.1.dist-info/RECORD
